sim2bids/__init__.py
sim2bids/cli.py
sim2bids/sim2bids.py
sim2bids/utils.py
sim2bids/app/__init__.py
sim2bids/app/app.py
sim2bids/app/utils.py
sim2bids/convert/__init__.py
sim2bids/convert/convert.py
sim2bids/generate/__init__.py
sim2bids/generate/structure.py
sim2bids/generate/subjects.py
sim2bids/generate/zip_traversal.py
sim2bids/preprocess/__init__.py
sim2bids/preprocess/preprocess.py
sim2bids/templates/__init__.py
sim2bids/templates/templates.py
sim2bids/templates/user_guide.py
sim2bids/validate/__init__.py
sim2bids/validate/validate.py
sim2bids-1.1.2.dist-info/LICENSE
sim2bids-1.1.2.dist-info/METADATA
sim2bids-1.1.2.dist-info/WHEEL
sim2bids-1.1.2.dist-info/top_level.txt
sim2bids-1.1.2.dist-info/RECORD
