Metadata-Version: 2.1
Name: sim2bids
Version: 1.1.2
Summary: App to preprocess and convert simulation data
Home-page: https://github.com/dissagaliyeva/incf
Author: Dinara Issagaliyeva
Author-email: dinarissaa@gmail.com
License: MIT license
Keywords: simulations,computational data,Holoviz Panel
Platform: UNKNOWN
Classifier: Development Status :: 2 - Pre-Alpha
Classifier: Intended Audience :: Science/Research
Classifier: Operating System :: Microsoft :: Windows :: Windows 11
Classifier: License :: OSI Approved :: MIT License
Classifier: Programming Language :: Python :: 3
Requires-Python: >=3.6
License-File: LICENSE
Requires-Dist: numpy
Requires-Dist: pandas
Requires-Dist: h5py
Requires-Dist: panel (~=0.13.1)
Requires-Dist: holoviews
Requires-Dist: param (~=1.12.0)
Requires-Dist: graphviz
Requires-Dist: mat73
Requires-Dist: pylems-py2xml
